winzy_txt2img_val_town/__init__.py
winzy_txt2img_val_town-0.0.1.dist-info/LICENSE
winzy_txt2img_val_town-0.0.1.dist-info/METADATA
winzy_txt2img_val_town-0.0.1.dist-info/WHEEL
winzy_txt2img_val_town-0.0.1.dist-info/entry_points.txt
winzy_txt2img_val_town-0.0.1.dist-info/top_level.txt
winzy_txt2img_val_town-0.0.1.dist-info/RECORD
