Metadata-Version: 2.1
Name: winzy-txt2img-val-town
Version: 0.0.1
Summary: Text to Image Gen Using Val Town's imggenurl 
Author: Sukhbinder Singh
License: Apache-2.0
Project-URL: Homepage, https://github.com/sukhbinder/winzy-txt2img-val-town
Project-URL: Changelog, https://github.com/sukhbinder/winzy-txt2img-val-town/releases
Project-URL: Issues, https://github.com/sukhbinder/winzy-txt2img-val-town/issues
Project-URL: CI, https://github.com/sukhbinder/winzy-txt2img-val-town/actions
Classifier: License :: OSI Approved :: Apache Software License
License-File: LICENSE
Requires-Dist: winzy
Requires-Dist: requests
Provides-Extra: test
Requires-Dist: pytest; extra == "test"
